<?xml version="1.0" encoding="utf-8"?>
<maxi-xml>
  <id>41017045</id>
  <typeId>46</typeId>
  <sex>0</sex>
  <date>2024-01-28T14:44:00+01:00</date>
  <status>3</status>
  <heat index="1">
    <athlete index="1">
      <id>4856401</id>
      <teamId>74572</teamId>
      <performance>3283.38</performance>
      <placing>5</placing>
      <score>937</score>
    </athlete>
    <athlete index="2">
      <id>5021091</id>
      <teamId>92121</teamId>
      <performance>3394.83</performance>
      <placing>6</placing>
      <score>858</score>
    </athlete>
    <athlete index="3">
      <id>5076082</id>
      <teamId>91364</teamId>
      <performance>3201.30</performance>
      <placing>4</placing>
      <score>996</score>
    </athlete>
    <athlete index="4">
      <id>5082768</id>
      <teamId>31337</teamId>
      <performance>3113.17</performance>
      <placing>1</placing>
      <score>1058</score>
    </athlete>
    <athlete index="5">
      <id>5110497</id>
      <teamId>31292</teamId>
      <performance>3173.38</performance>
      <placing>3</placing>
      <score>1016</score>
    </athlete>
    <athlete index="6">
      <id>5194038</id>
      <teamId>53222</teamId>
      <performance>3151.97</performance>
      <placing>2</placing>
      <score>1031</score>
    </athlete>
    <athlete index="7">
      <id>5231438</id>
      <teamId>7818</teamId>
      <performance>3429.09</performance>
      <placing>7</placing>
      <score>834</score>
    </athlete>
    <athlete index="8">
      <id>5314650</id>
      <teamId>24833</teamId>
      <performance>3451.85</performance>
      <placing>8</placing>
      <score>818</score>
    </athlete>
  </heat>
</maxi-xml>
