<?xml version="1.0" encoding="utf-8"?>
<maxi-xml>
  <id>42333132</id>
  <typeId>31</typeId>
  <sex>0</sex>
  <date>2024-07-21T15:12:00+02:00</date>
  <status>3</status>
  <heat index="1">
    <athlete index="1">
      <id>4721910</id>
      <teamId>9875</teamId>
      <performance>18.13</performance>
      <placing>3</placing>
      <score>797</score>
    </athlete>
    <athlete index="2">
      <id>4857254</id>
      <teamId>83164</teamId>
      <performance>17.02</performance>
      <placing>6</placing>
      <score>713</score>
    </athlete>
    <athlete index="3">
      <id>4965837</id>
      <teamId>81</teamId>
      <performance>19.01</performance>
      <placing>1</placing>
      <score>864</score>
    </athlete>
    <athlete index="4">
      <id>5110817</id>
      <teamId>90877</teamId>
      <performance>17.97</performance>
      <placing>4</placing>
      <score>785</score>
    </athlete>
    <athlete index="5">
      <id>5136170</id>
      <teamId>91120</teamId>
      <performance>19.00</performance>
      <placing>2</placing>
      <attitude>1</attitude>
      <score>863</score>
    </athlete>
    <athlete index="6">
      <id>5270700</id>
      <teamId>2437</teamId>
      <performance>17.48</performance>
      <placing>5</placing>
      <score>748</score>
    </athlete>
    <athlete index="7">
      <id>5399844</id>
      <teamId>978</teamId>
      <performance>13.49</performance>
      <placing>7</placing>
      <score>445</score>
    </athlete>
  </heat>
</maxi-xml>
