<?xml version="1.0" encoding="utf-8"?>
<maxi-xml>
  <id>42332256</id>
  <typeId>26</typeId>
  <sex>1</sex>
  <date>2024-06-16T14:58:00+02:00</date>
  <status>3</status>
  <heat index="1">
    <athlete index="1">
      <id>4689720</id>
      <teamId>980</teamId>
      <performance>1.73</performance>
      <placing>1</placing>
      <score>919</score>
    </athlete>
    <athlete index="2">
      <id>4771452</id>
      <teamId>9875</teamId>
      <performance>1.61</performance>
      <placing>3</placing>
      <score>815</score>
    </athlete>
    <athlete index="3">
      <id>4929566</id>
      <teamId>88860</teamId>
      <performance>1.44</performance>
      <placing>6</placing>
      <score>667</score>
    </athlete>
    <athlete index="4">
      <id>4999424</id>
      <teamId>83164</teamId>
      <performance>1.57</performance>
      <placing>4</placing>
      <score>780</score>
    </athlete>
    <athlete index="5">
      <id>5056892</id>
      <teamId>53735</teamId>
      <performance>1.55</performance>
      <placing>5</placing>
      <score>763</score>
    </athlete>
    <athlete index="6">
      <id>5057846</id>
      <teamId>91120</teamId>
      <performance>1.63</performance>
      <placing>2</placing>
      <attitude>1</attitude>
      <score>832</score>
    </athlete>
    <athlete index="7">
      <id>5249172</id>
      <teamId>18628</teamId>
      <performance>1.17</performance>
      <placing>7</placing>
      <score>433</score>
    </athlete>
    <athlete index="8">
      <id>5401503</id>
      <teamId>81</teamId>
      <performance>1.16</performance>
      <placing>8</placing>
      <score>424</score>
    </athlete>
  </heat>
</maxi-xml>
