<?xml version="1.0" encoding="utf-8"?>
<maxi-xml>
  <id>41017518</id>
  <typeId>53</typeId>
  <sex>1</sex>
  <date>2024-02-18T14:42:00+01:00</date>
  <status>3</status>
  <heat index="1">
    <athlete index="1">
      <id>4739268</id>
      <teamId>53222</teamId>
      <performance>9565.32</performance>
      <placing>3</placing>
      <score>1017</score>
    </athlete>
    <athlete index="2">
      <id>4986635</id>
      <teamId>91364</teamId>
      <performance>9238.97</performance>
      <placing>1</placing>
      <score>1094</score>
    </athlete>
    <athlete index="3">
      <id>4992340</id>
      <teamId>90877</teamId>
      <performance>9445.71</performance>
      <placing>2</placing>
      <score>1045</score>
    </athlete>
    <athlete index="4">
      <id>5021088</id>
      <teamId>92121</teamId>
      <performance>9908.57</performance>
      <placing>6</placing>
      <score>936</score>
    </athlete>
    <athlete index="5">
      <id>5104796</id>
      <teamId>69187</teamId>
      <performance>9719.90</performance>
      <placing>4</placing>
      <score>981</score>
    </athlete>
    <athlete index="6">
      <id>5192182</id>
      <teamId>91120</teamId>
      <performance>9812.66</performance>
      <placing>5</placing>
      <attitude>1</attitude>
      <score>959</score>
    </athlete>
    <athlete index="7">
      <id>5267486</id>
      <teamId>89719</teamId>
      <performance>10215.01</performance>
      <placing>7</placing>
      <score>864</score>
    </athlete>
  </heat>
</maxi-xml>
