<?xml version="1.0" encoding="utf-8"?>
<maxi-xml>
  <id>41015959</id>
  <typeId>34</typeId>
  <sex>0</sex>
  <date>2024-02-04T15:24:00+01:00</date>
  <status>3</status>
  <heat index="1">
    <athlete index="1">
      <id>4523512</id>
      <teamId>12233</teamId>
      <performance>72.01</performance>
      <placing>1</placing>
      <score>1010</score>
    </athlete>
    <athlete index="2">
      <id>4724344</id>
      <teamId>2585</teamId>
      <performance>60.60</performance>
      <placing>5</placing>
      <score>758</score>
    </athlete>
    <athlete index="3">
      <id>4828108</id>
      <teamId>81</teamId>
      <performance>63.70</performance>
      <placing>4</placing>
      <score>827</score>
    </athlete>
    <athlete index="4">
      <id>4866909</id>
      <teamId>76442</teamId>
      <performance>60.31</performance>
      <placing>6</placing>
      <score>752</score>
    </athlete>
    <athlete index="5">
      <id>4940530</id>
      <teamId>980</teamId>
      <performance>64.98</performance>
      <placing>2</placing>
      <score>855</score>
    </athlete>
    <athlete index="6">
      <id>5024063</id>
      <teamId>53735</teamId>
      <performance>64.37</performance>
      <placing>3</placing>
      <score>842</score>
    </athlete>
    <athlete index="7">
      <id>5215237</id>
      <teamId>58067</teamId>
      <performance>50.72</performance>
      <placing>7</placing>
      <score>541</score>
    </athlete>
  </heat>
</maxi-xml>
