<?xml version="1.0" encoding="utf-8"?>
<maxi-xml>
  <id>41015722</id>
  <typeId>34</typeId>
  <sex>0</sex>
  <date>2024-01-21T15:24:00+01:00</date>
  <status>3</status>
  <heat index="1">
    <athlete index="1">
      <id>4724344</id>
      <teamId>2585</teamId>
      <performance>62.76</performance>
      <placing>5</placing>
      <score>806</score>
    </athlete>
    <athlete index="2">
      <id>4815235</id>
      <teamId>2437</teamId>
      <performance>66.89</performance>
      <placing>1</placing>
      <score>897</score>
    </athlete>
    <athlete index="3">
      <id>4828108</id>
      <teamId>81</teamId>
      <performance>64.06</performance>
      <placing>3</placing>
      <score>835</score>
    </athlete>
    <athlete index="4">
      <id>4866909</id>
      <teamId>76442</teamId>
      <performance>63.81</performance>
      <placing>4</placing>
      <score>829</score>
    </athlete>
    <athlete index="5">
      <id>5008415</id>
      <teamId>978</teamId>
      <performance>66.45</performance>
      <placing>2</placing>
      <score>887</score>
    </athlete>
    <athlete index="6">
      <id>5132342</id>
      <teamId>7408</teamId>
      <performance>57.77</performance>
      <placing>6</placing>
      <score>696</score>
    </athlete>
    <athlete index="7">
      <id>5169679</id>
      <teamId>657</teamId>
      <performance>46.83</performance>
      <placing>8</placing>
      <score>455</score>
    </athlete>
    <athlete index="8">
      <id>5215237</id>
      <teamId>58067</teamId>
      <performance>50.92</performance>
      <placing>7</placing>
      <score>545</score>
    </athlete>
  </heat>
</maxi-xml>
